<?xml version="1.0" encoding="utf-8" standalone="yes"?>
<?xml-stylesheet type="text/xsl" href="NounRenderTemplate.xslt"?>
<Eintrag category="Substantiv">
<Stichwort>Tür</Stichwort>
<Einheit>1</Einheit>
<Anteil>3</Anteil>
<Genus>die</Genus>
<Pluralform>Türen</Pluralform>
<GenitivSingular></GenitivSingular>
<zusammengesetzteWörter>
<KompositaCollection>
<K_>Türklingel</K_>
<K_>Türschloss</K_>
<_K link="116.xml">Gartentür</_K>
</KompositaCollection>
<abgeleiteteWörter/>
</zusammengesetzteWörter>
<Synonymegruppe/>
<Antonymegruppe/>
<Kollokationen/>
<AllgemeineErläuterungen>
<Eintrag>
<Chinesisch>门</Chinesisch>
<BeispielSammlung>
<Beispiel>
<Satz>Das ist eine Tür.</Satz>
<Übersetzung></Übersetzung>
</Beispiel>
</BeispielSammlung>
</Eintrag>
</AllgemeineErläuterungen>
</Eintrag>