<?xml version="1.0" encoding="UTF-8"?>
<Eintrag><Stichwort>absatteln</Stichwort><Infinitiv>absatteln</Infinitiv><Pr채sen><ich>sattle ab</ich><du>sattelst ab</du><er_sie_es>sattelt ab</er_sie_es><wir>satteln ab</wir><ihr>sattelt ab</ihr><sie_Sie>satteln ab</sie_Sie></Pr채sen><Pr채teritum><ich>sattelte ab</ich><du>satteltest ab</du><er_sie_es>sattelte ab</er_sie_es><wir>sattelten ab</wir><ihr>satteltet ab</ihr><sie_Sie>sattelten ab</sie_Sie></Pr채teritum><Pratizip>hat abgesattelt </Pratizip></Eintrag>