<?xml version="1.0" encoding="UTF-8"?>
<Eintrag><Stichwort>abschlachten</Stichwort><Infinitiv>abschlachten</Infinitiv><Pr채sen><ich>schlachte ab</ich><du>schlachtest ab</du><er_sie_es>schlachtet ab</er_sie_es><wir>schlachten ab</wir><ihr>schlachtet ab</ihr><sie_Sie>schlachten ab</sie_Sie></Pr채sen><Pr채teritum><ich>schlachtete ab</ich><du>schlachtetest ab</du><er_sie_es>schlachtete ab</er_sie_es><wir>schlachteten ab</wir><ihr>schlachtetet ab</ihr><sie_Sie>schlachteten ab</sie_Sie></Pr채teritum><Pratizip>hat abgeschlachtet </Pratizip></Eintrag>