<?xml version="1.0" encoding="UTF-8"?>
<Eintrag><Stichwort>aufgliedern</Stichwort><Infinitiv>aufgliedern</Infinitiv><Pr채sen><ich>gliedere auf</ich><du>gliedre auf</du><er_sie_es>gliederst auf</er_sie_es><wir>gliedert auf</wir><ihr>gliedern auf</ihr><sie_Sie>gliedert auf</sie_Sie></Pr채sen><Pr채teritum><ich>Sie</ich><du>gliederte auf</du><er_sie_es>gliedertest auf</er_sie_es><wir>gliederte auf</wir><ihr>gliederten auf</ihr><sie_Sie>gliedertet auf</sie_Sie></Pr채teritum><Pratizip>hast aufgegliedert </Pratizip></Eintrag>