<?xml version="1.0" encoding="UTF-8"?>
<Eintrag><Stichwort>aufstecken</Stichwort><Infinitiv>aufstecken</Infinitiv><Pr채sen><ich>stecke auf</ich><du>steckst auf</du><er_sie_es>steckt auf</er_sie_es><wir>stecken auf</wir><ihr>steckt auf</ihr><sie_Sie>stecken auf</sie_Sie></Pr채sen><Pr채teritum><ich>steckte auf</ich><du>stecktest auf</du><er_sie_es>steckte auf</er_sie_es><wir>steckten auf</wir><ihr>stecktet auf</ihr><sie_Sie>steckten auf</sie_Sie></Pr채teritum><Pratizip>hat aufgesteckt </Pratizip></Eintrag>