<?xml version="1.0" encoding="UTF-8"?>
<Eintrag><Stichwort>aufschichten</Stichwort><Infinitiv>aufschichten</Infinitiv><Pr채sen><ich>schichte auf</ich><du>schichtest auf</du><er_sie_es>schichtet auf</er_sie_es><wir>schichten auf</wir><ihr>schichtet auf</ihr><sie_Sie>schichten auf</sie_Sie></Pr채sen><Pr채teritum><ich>schichtete auf</ich><du>schichtetest auf</du><er_sie_es>schichtete auf</er_sie_es><wir>schichteten auf</wir><ihr>schichtetet auf</ihr><sie_Sie>schichteten auf</sie_Sie></Pr채teritum><Pratizip>hat aufgeschichtet </Pratizip></Eintrag>