<?xml version="1.0" encoding="UTF-8"?>
<Eintrag><Stichwort>auseinanderbrechen</Stichwort><Infinitiv>auseinanderbrechen</Infinitiv><Pr채sen><ich>breche auseinander</ich><du>brichst auseinander</du><er_sie_es>bricht auseinander</er_sie_es><wir>brechen auseinander</wir><ihr>brecht auseinander</ihr><sie_Sie>brechen auseinander</sie_Sie></Pr채sen><Pr채teritum><ich>brach auseinander</ich><du>brachst auseinander</du><er_sie_es>brach auseinander</er_sie_es><wir>brachen auseinander</wir><ihr>bracht auseinander</ihr><sie_Sie>brachen auseinander</sie_Sie></Pr채teritum><Pratizip>hat auseinandergebrochen </Pratizip></Eintrag>