<?xml version="1.0" encoding="UTF-8"?>
<Eintrag><Stichwort>ausforschen</Stichwort><Infinitiv>ausforschen</Infinitiv><Pr채sen><ich>forsche aus</ich><du>forscht aus</du><er_sie_es>forscht aus</er_sie_es><wir>forschen aus</wir><ihr>forscht aus</ihr><sie_Sie>forschen aus</sie_Sie></Pr채sen><Pr채teritum><ich>forschte aus</ich><du>forschtest aus</du><er_sie_es>forschte aus</er_sie_es><wir>forschten aus</wir><ihr>forschtet aus</ihr><sie_Sie>forschten aus</sie_Sie></Pr채teritum><Pratizip>hat ausgeforscht </Pratizip></Eintrag>