<?xml version="1.0" encoding="UTF-8"?>
<Eintrag><Stichwort>ausgleiten</Stichwort><Infinitiv>ausgleiten</Infinitiv><Pr채sen><ich>gleite aus</ich><du>gleitest aus</du><er_sie_es>gleitet aus</er_sie_es><wir>gleiten aus</wir><ihr>gleitet aus</ihr><sie_Sie>gleiten aus</sie_Sie></Pr채sen><Pr채teritum><ich>glitt aus</ich><du>glittest aus</du><er_sie_es>glitt aus</er_sie_es><wir>glitten aus</wir><ihr>glittet aus</ihr><sie_Sie>glitten aus</sie_Sie></Pr채teritum><Pratizip>ist ausgeglitten </Pratizip></Eintrag>