<?xml version="1.0" encoding="UTF-8"?>
<Eintrag><Stichwort>ausmontieren</Stichwort><Infinitiv>ausmontieren</Infinitiv><Pr채sen><ich>montiere aus</ich><du>montierst aus</du><er_sie_es>montiert aus</er_sie_es><wir>montieren aus</wir><ihr>montiert aus</ihr><sie_Sie>montieren aus</sie_Sie></Pr채sen><Pr채teritum><ich>montierte aus</ich><du>montiertest aus</du><er_sie_es>montierte aus</er_sie_es><wir>montierten aus</wir><ihr>montiertet aus</ihr><sie_Sie>montierten aus</sie_Sie></Pr채teritum><Pratizip>hat ausmontiert </Pratizip></Eintrag>