<?xml version="1.0" encoding="UTF-8"?>
<Eintrag><Stichwort>dafürhalten</Stichwort><Infinitiv>dafürhalten</Infinitiv><Präsen><ich>halte dafür</ich><du>hältst dafür</du><er_sie_es>hält dafür</er_sie_es><wir>halten dafür</wir><ihr>haltet dafür</ihr><sie_Sie>halten dafür</sie_Sie></Präsen><Präteritum><ich>hielt dafür</ich><du>hieltest dafür</du><er_sie_es>hielt dafür</er_sie_es><wir>hielten dafür</wir><ihr>hieltet dafür</ihr><sie_Sie>hielten dafür</sie_Sie></Präteritum><Pratizip>hat dafürgehalten </Pratizip></Eintrag>