<?xml version="1.0" encoding="UTF-8"?>
<Eintrag><Stichwort>dichtmachen</Stichwort><Infinitiv>dichtmachen</Infinitiv><Pr채sen><ich>mache dicht</ich><du>machst dicht</du><er_sie_es>macht dicht</er_sie_es><wir>machen dicht</wir><ihr>macht dicht</ihr><sie_Sie>machen dicht</sie_Sie></Pr채sen><Pr채teritum><ich>machte dicht</ich><du>machtest dicht</du><er_sie_es>machte dicht</er_sie_es><wir>machten dicht</wir><ihr>machtet dicht</ihr><sie_Sie>machten dicht</sie_Sie></Pr채teritum><Pratizip>hat dichtgemacht </Pratizip></Eintrag>