<?xml version="1.0" encoding="UTF-8"?>
<Eintrag><Stichwort>einpfropfen</Stichwort><Infinitiv>einpfropfen</Infinitiv><Pr채sen><ich>pfropfe ein</ich><du>pfropfst ein</du><er_sie_es>pfropft ein</er_sie_es><wir>pfropfen ein</wir><ihr>pfropft ein</ihr><sie_Sie>pfropfen ein</sie_Sie></Pr채sen><Pr채teritum><ich>pfropfte ein</ich><du>pfropftest ein</du><er_sie_es>pfropfte ein</er_sie_es><wir>pfropften ein</wir><ihr>pfropftet ein</ihr><sie_Sie>pfropften ein</sie_Sie></Pr채teritum><Pratizip>hat eingepfropft </Pratizip></Eintrag>