<?xml version="1.0" encoding="UTF-8"?>
<Eintrag><Stichwort>ermöglichen</Stichwort><Infinitiv>ermöglichen</Infinitiv><Präsen><ich>ermögliche</ich><du>ermöglichst</du><er_sie_es>ermöglicht</er_sie_es><wir>ermöglichen</wir><ihr>ermöglicht</ihr><sie_Sie>ermöglichen</sie_Sie></Präsen><Präteritum><ich>ermöglichte</ich><du>ermöglichtest</du><er_sie_es>ermöglichte</er_sie_es><wir>ermöglichten</wir><ihr>ermöglichtet</ihr><sie_Sie>ermöglichten</sie_Sie></Präteritum><Pratizip>hat ermöglicht </Pratizip></Eintrag>