<?xml version="1.0" encoding="UTF-8"?>
<Eintrag><Stichwort>fortbestehen</Stichwort><Infinitiv>fortbestehen</Infinitiv><Pr채sen><ich>bestehe fort</ich><du>bestehst fort</du><er_sie_es>besteht fort</er_sie_es><wir>bestehen fort</wir><ihr>besteht fort</ihr><sie_Sie>bestehen fort</sie_Sie></Pr채sen><Pr채teritum><ich>bestand fort</ich><du>bestand(e)st fort</du><er_sie_es>bestand fort</er_sie_es><wir>bestanden fort</wir><ihr>bestandet fort</ihr><sie_Sie>bestanden fort</sie_Sie></Pr채teritum><Pratizip>hat fortbestanden </Pratizip></Eintrag>