<?xml version="1.0" encoding="UTF-8"?>
<Eintrag><Stichwort>heruntergleiten</Stichwort><Infinitiv>heruntergleiten</Infinitiv><Pr채sen><ich>gleite herunter</ich><du>gleitest herunter</du><er_sie_es>gleitet herunter</er_sie_es><wir>gleiten herunter</wir><ihr>gleitet herunter</ihr><sie_Sie>gleiten herunter</sie_Sie></Pr채sen><Pr채teritum><ich>glitt herunter</ich><du>glittest herunter</du><er_sie_es>glitt herunter</er_sie_es><wir>glitten herunter</wir><ihr>glittet herunter</ihr><sie_Sie>glitten herunter</sie_Sie></Pr채teritum><Pratizip>ist heruntergeglitten </Pratizip></Eintrag>