<?xml version="1.0" encoding="UTF-8"?>
<Eintrag><Stichwort>herüberholen</Stichwort><Infinitiv>herüberholen</Infinitiv><Präsen><ich>hole herüber</ich><du>holst herüber</du><er_sie_es>holt herüber</er_sie_es><wir>holen herüber</wir><ihr>holt herüber</ihr><sie_Sie>holen herüber</sie_Sie></Präsen><Präteritum><ich>holte herüber</ich><du>holtest herüber</du><er_sie_es>holte herüber</er_sie_es><wir>holten herüber</wir><ihr>holtet herüber</ihr><sie_Sie>holten herüber</sie_Sie></Präteritum><Pratizip>hat herübergeholt </Pratizip></Eintrag>