<?xml version="1.0" encoding="UTF-8"?>
<Eintrag><Stichwort>hinarbeiten</Stichwort><Infinitiv>hinarbeiten</Infinitiv><Pr채sen><ich>arbeite hin</ich><du>arbeitest hin</du><er_sie_es>arbeitet hin</er_sie_es><wir>arbeiten hin</wir><ihr>arbeitet hin</ihr><sie_Sie>arbeiten hin</sie_Sie></Pr채sen><Pr채teritum><ich>arbeitete hin</ich><du>arbeitetest hin</du><er_sie_es>arbeitete hin</er_sie_es><wir>arbeiteten hin</wir><ihr>arbeitetet hin</ihr><sie_Sie>arbeiteten hin</sie_Sie></Pr채teritum><Pratizip>hat hingearbeitet </Pratizip></Eintrag>