<?xml version="1.0" encoding="UTF-8"?>
<Eintrag><Stichwort>hinausfahren</Stichwort><Infinitiv>hinausfahren</Infinitiv><Präsen><ich>fahre hinaus</ich><du>fährst hinaus</du><er_sie_es>fährt hinaus</er_sie_es><wir>fahren hinaus</wir><ihr>fahrt hinaus</ihr><sie_Sie>fahren hinaus</sie_Sie></Präsen><Präteritum><ich>fuhr hinaus</ich><du>fuhrst hinaus</du><er_sie_es>fuhr hinaus</er_sie_es><wir>fuhren hinaus</wir><ihr>fuhrt hinaus</ihr><sie_Sie>fuhren hinaus</sie_Sie></Präteritum><Pratizip>ist hinausgefahren </Pratizip></Eintrag>