<?xml version="1.0" encoding="UTF-8"?>
<Eintrag><Stichwort>hinauflaufen</Stichwort><Infinitiv>hinauflaufen</Infinitiv><Präsen><ich>laufe hinauf</ich><du>läufst hinauf</du><er_sie_es>läuft hinauf</er_sie_es><wir>laufen hinauf</wir><ihr>lauft hinauf</ihr><sie_Sie>laufen hinauf</sie_Sie></Präsen><Präteritum><ich>lief hinauf</ich><du>liefst hinauf</du><er_sie_es>lief hinauf</er_sie_es><wir>liefen hinauf</wir><ihr>lieft hinauf</ihr><sie_Sie>liefen hinauf</sie_Sie></Präteritum><Pratizip>ist hinaufgelaufen </Pratizip></Eintrag>