<?xml version="1.0" encoding="UTF-8"?>
<Eintrag><Stichwort>hinauswandern</Stichwort><Infinitiv>hinauswandern</Infinitiv><Pr채sen><ich>wandere hinaus</ich><du>wandre hinaus</du><er_sie_es>wanderst hinaus</er_sie_es><wir>wandert hinaus</wir><ihr>wandern hinaus</ihr><sie_Sie>wandert hinaus</sie_Sie></Pr채sen><Pr채teritum><ich>Sie</ich><du>wanderte hinaus</du><er_sie_es>wandertest hinaus</er_sie_es><wir>wanderte hinaus</wir><ihr>wanderten hinaus</ihr><sie_Sie>wandertet hinaus</sie_Sie></Pr채teritum><Pratizip>hast hinausgewandert </Pratizip></Eintrag>