<?xml version="1.0" encoding="UTF-8"?>
<Eintrag><Stichwort>hinterübersinken</Stichwort><Infinitiv>hinterübersinken</Infinitiv><Präsen><ich>sinke hinterüber</ich><du>sinkst hinterüber</du><er_sie_es>sinkt hinterüber</er_sie_es><wir>sinken hinterüber</wir><ihr>sinkt hinterüber</ihr><sie_Sie>sinken hinterüber</sie_Sie></Präsen><Präteritum><ich>sank hinterüber</ich><du>sankst hinterüber</du><er_sie_es>sank hinterüber</er_sie_es><wir>sanken hinterüber</wir><ihr>sankt hinterüber</ihr><sie_Sie>sanken hinterüber</sie_Sie></Präteritum><Pratizip>ist hinterübergesunken </Pratizip></Eintrag>