<?xml version="1.0" encoding="UTF-8"?>
<Eintrag><Stichwort>hinüberziehen</Stichwort><Infinitiv>hinüberziehen</Infinitiv><Präsen><ich>ziehe hinüber</ich><du>ziehst hinüber</du><er_sie_es>zieht hinüber</er_sie_es><wir>ziehen hinüber</wir><ihr>zieht hinüber</ihr><sie_Sie>ziehen hinüber</sie_Sie></Präsen><Präteritum><ich>zog hinüber</ich><du>zogst hinüber</du><er_sie_es>zog hinüber</er_sie_es><wir>zogen hinüber</wir><ihr>zogt hinüber</ihr><sie_Sie>zogen hinüber</sie_Sie></Präteritum><Pratizip>hat hinübergezogen </Pratizip></Eintrag>