<?xml version="1.0" encoding="UTF-8"?>
<Eintrag><Stichwort>hinübersehen</Stichwort><Infinitiv>hinübersehen</Infinitiv><Präsen><ich>sehe hinüber</ich><du>siehst hinüber</du><er_sie_es>sieht hinüber</er_sie_es><wir>sehen hinüber</wir><ihr>seht hinüber</ihr><sie_Sie>sehen hinüber</sie_Sie></Präsen><Präteritum><ich>sah hinüber</ich><du>sah(e)st hinüber</du><er_sie_es>sah hinüber</er_sie_es><wir>sahen hinüber</wir><ihr>saht hinüber</ihr><sie_Sie>sahen hinüber</sie_Sie></Präteritum><Pratizip>hat hinübergesehen </Pratizip></Eintrag>