<?xml version="1.0" encoding="UTF-8"?>
<Eintrag><Stichwort>hochschrauben</Stichwort><Infinitiv>hochschrauben</Infinitiv><Pr채sen><ich>schraube hoch</ich><du>schraubst hoch</du><er_sie_es>schraubt hoch</er_sie_es><wir>schrauben hoch</wir><ihr>schraubt hoch</ihr><sie_Sie>schrauben hoch</sie_Sie></Pr채sen><Pr채teritum><ich>schraubte hoch</ich><du>schraubtest hoch</du><er_sie_es>schraubte hoch</er_sie_es><wir>schraubten hoch</wir><ihr>schraubtet hoch</ihr><sie_Sie>schraubten hoch</sie_Sie></Pr채teritum><Pratizip>hat hochgeschraubt </Pratizip></Eintrag>