<?xml version="1.0" encoding="UTF-8"?>
<Eintrag><Stichwort>kopfstehen</Stichwort><Infinitiv>kopfstehen</Infinitiv><Pr채sen><ich>stehe kopf</ich><du>stehst kopf</du><er_sie_es>steht kopf</er_sie_es><wir>stehen kopf</wir><ihr>steht kopf</ihr><sie_Sie>stehen kopf</sie_Sie></Pr채sen><Pr채teritum><ich>stand kopf</ich><du>stand(e)st kopf</du><er_sie_es>stand kopf</er_sie_es><wir>standen kopf</wir><ihr>standet kopf</ihr><sie_Sie>standen kopf</sie_Sie></Pr채teritum><Pratizip>hat kopfgestanden </Pratizip></Eintrag>