<?xml version="1.0" encoding="UTF-8"?>
<Eintrag><Stichwort>kostümieren</Stichwort><Infinitiv>kostümieren</Infinitiv><Präsen><ich>kostümiere</ich><du>kostümierst</du><er_sie_es>kostümiert</er_sie_es><wir>kostümieren</wir><ihr>kostümiert</ihr><sie_Sie>kostümieren</sie_Sie></Präsen><Präteritum><ich>kostümierte</ich><du>kostümiertest</du><er_sie_es>kostümierte</er_sie_es><wir>kostümierten</wir><ihr>kostümiertet</ihr><sie_Sie>kostümierten</sie_Sie></Präteritum><Pratizip>hat kostümiert </Pratizip></Eintrag>