<?xml version="1.0" encoding="UTF-8"?>
<Eintrag><Stichwort>losdreschen</Stichwort><Infinitiv>losdreschen</Infinitiv><Pr채sen><ich>dresche los</ich><du>drischst los</du><er_sie_es>drischt los</er_sie_es><wir>dreschen los</wir><ihr>drescht los</ihr><sie_Sie>dreschen los</sie_Sie></Pr채sen><Pr채teritum><ich>drosch los</ich><du>droschst los</du><er_sie_es>drosch los</er_sie_es><wir>droschen los</wir><ihr>droscht los</ihr><sie_Sie>droschen los</sie_Sie></Pr채teritum><Pratizip>hat losgedroschen </Pratizip></Eintrag>