<?xml version="1.0" encoding="UTF-8"?>
<Eintrag><Stichwort>miterleben</Stichwort><Infinitiv>miterleben</Infinitiv><Pr채sen><ich>erlebe mit</ich><du>erlebst mit</du><er_sie_es>erlebt mit</er_sie_es><wir>erleben mit</wir><ihr>erlebt mit</ihr><sie_Sie>erleben mit</sie_Sie></Pr채sen><Pr채teritum><ich>erlebte mit</ich><du>erlebtest mit</du><er_sie_es>erlebte mit</er_sie_es><wir>erlebten mit</wir><ihr>erlebtet mit</ihr><sie_Sie>erlebten mit</sie_Sie></Pr채teritum><Pratizip>hat miterlebt </Pratizip></Eintrag>