<?xml version="1.0" encoding="UTF-8"?>
<Eintrag><Stichwort>niederstürzen</Stichwort><Infinitiv>niederstürzen</Infinitiv><Präsen><ich>stürze nieder</ich><du>stürzt nieder</du><er_sie_es>stürzt nieder</er_sie_es><wir>stürzen nieder</wir><ihr>stürzt nieder</ihr><sie_Sie>stürzen nieder</sie_Sie></Präsen><Präteritum><ich>stürzte nieder</ich><du>stürztest nieder</du><er_sie_es>stürzte nieder</er_sie_es><wir>stürzten nieder</wir><ihr>stürztet nieder</ihr><sie_Sie>stürzten nieder</sie_Sie></Präteritum><Pratizip>hat niedergestürzt </Pratizip></Eintrag>