<?xml version="1.0" encoding="UTF-8"?>
<Eintrag><Stichwort>porträtieren</Stichwort><Infinitiv>porträtieren</Infinitiv><Präsen><ich>porträtiere</ich><du>porträtierst</du><er_sie_es>porträtiert</er_sie_es><wir>porträtieren</wir><ihr>porträtiert</ihr><sie_Sie>porträtieren</sie_Sie></Präsen><Präteritum><ich>porträtierte</ich><du>porträtiertest</du><er_sie_es>porträtierte</er_sie_es><wir>porträtierten</wir><ihr>porträtiertet</ihr><sie_Sie>porträtierten</sie_Sie></Präteritum><Pratizip>hat porträtiert </Pratizip></Eintrag>