<?xml version="1.0" encoding="UTF-8"?>
<Eintrag><Stichwort>ranschleichen</Stichwort><Infinitiv>ranschleichen</Infinitiv><Pr채sen><ich>schleiche ran</ich><du>schleichst ran</du><er_sie_es>schleicht ran</er_sie_es><wir>schleichen ran</wir><ihr>schleicht ran</ihr><sie_Sie>schleichen ran</sie_Sie></Pr채sen><Pr채teritum><ich>schlich ran</ich><du>schlichst ran</du><er_sie_es>schlich ran</er_sie_es><wir>schlichen ran</wir><ihr>schlicht ran</ihr><sie_Sie>schlichen ran</sie_Sie></Pr채teritum><Pratizip>ist rangeschlichen </Pratizip></Eintrag>