<?xml version="1.0" encoding="UTF-8"?>
<Eintrag><Stichwort>reinstoßen</Stichwort><Infinitiv>reinstoßen</Infinitiv><Präsen><ich>stoße rein</ich><du>stößt rein</du><er_sie_es>stößt rein</er_sie_es><wir>stoßen rein</wir><ihr>stoßt rein</ihr><sie_Sie>stoßen rein</sie_Sie></Präsen><Präteritum><ich>stieß rein</ich><du>stießest rein</du><er_sie_es>stieß rein</er_sie_es><wir>stießen rein</wir><ihr>stießt rein</ihr><sie_Sie>stießen rein</sie_Sie></Präteritum><Pratizip>hat reingestoßen </Pratizip></Eintrag>