<?xml version="1.0" encoding="UTF-8"?>
<Eintrag><Stichwort>relativieren</Stichwort><Infinitiv>relativieren</Infinitiv><Pr채sen><ich>relativiere</ich><du>relativierst</du><er_sie_es>relativiert</er_sie_es><wir>relativieren</wir><ihr>relativiert</ihr><sie_Sie>relativieren</sie_Sie></Pr채sen><Pr채teritum><ich>relativierte</ich><du>relativiertest</du><er_sie_es>relativierte</er_sie_es><wir>relativierten</wir><ihr>relativiertet</ihr><sie_Sie>relativierten</sie_Sie></Pr채teritum><Pratizip>hat relativiert </Pratizip></Eintrag>