<?xml version="1.0" encoding="UTF-8"?>
<Eintrag><Stichwort>runterkriechen</Stichwort><Infinitiv>runterkriechen</Infinitiv><Pr채sen><ich>krieche runter</ich><du>kriechst runter</du><er_sie_es>kriecht runter</er_sie_es><wir>kriechen runter</wir><ihr>kriecht runter</ihr><sie_Sie>kriechen runter</sie_Sie></Pr채sen><Pr채teritum><ich>kroch runter</ich><du>krochst runter</du><er_sie_es>kroch runter</er_sie_es><wir>krochen runter</wir><ihr>krocht runter</ihr><sie_Sie>krochen runter</sie_Sie></Pr채teritum><Pratizip>ist runtergekrochen </Pratizip></Eintrag>