<?xml version="1.0" encoding="UTF-8"?>
<Eintrag><Stichwort>schlichten</Stichwort><Infinitiv>schlichten</Infinitiv><Pr채sen><ich>schlichte</ich><du>schlichtest</du><er_sie_es>schlichtet</er_sie_es><wir>schlichten</wir><ihr>schlichtet</ihr><sie_Sie>schlichten</sie_Sie></Pr채sen><Pr채teritum><ich>schlichtete</ich><du>schlichtetest</du><er_sie_es>schlichtete</er_sie_es><wir>schlichteten</wir><ihr>schlichtetet</ihr><sie_Sie>schlichteten</sie_Sie></Pr채teritum><Pratizip>hat geschlichtet </Pratizip></Eintrag>