<?xml version="1.0" encoding="UTF-8"?>
<Eintrag><Stichwort>schockieren</Stichwort><Infinitiv>schockieren</Infinitiv><Pr채sen><ich>schockiere</ich><du>schockierst</du><er_sie_es>schockiert</er_sie_es><wir>schockieren</wir><ihr>schockiert</ihr><sie_Sie>schockieren</sie_Sie></Pr채sen><Pr채teritum><ich>schockierte</ich><du>schockiertest</du><er_sie_es>schockierte</er_sie_es><wir>schockierten</wir><ihr>schockiertet</ihr><sie_Sie>schockierten</sie_Sie></Pr채teritum><Pratizip>hat schockiert </Pratizip></Eintrag>