<?xml version="1.0" encoding="UTF-8"?>
<Eintrag><Stichwort>schwarzhören</Stichwort><Infinitiv>schwarzhören</Infinitiv><Präsen><ich>höre schwarz</ich><du>hörst schwarz</du><er_sie_es>hört schwarz</er_sie_es><wir>hören schwarz</wir><ihr>hört schwarz</ihr><sie_Sie>hören schwarz</sie_Sie></Präsen><Präteritum><ich>hörte schwarz</ich><du>hörtest schwarz</du><er_sie_es>hörte schwarz</er_sie_es><wir>hörten schwarz</wir><ihr>hörtet schwarz</ihr><sie_Sie>hörten schwarz</sie_Sie></Präteritum><Pratizip>hat schwarzgehört </Pratizip></Eintrag>