<?xml version="1.0" encoding="UTF-8"?>
<Eintrag><Stichwort>sonnenbaden</Stichwort><Infinitiv>sonnenbaden</Infinitiv><Pr채sen><ich>bade sonnen</ich><du>badest sonnen</du><er_sie_es>badet sonnen</er_sie_es><wir>baden sonnen</wir><ihr>badet sonnen</ihr><sie_Sie>baden sonnen</sie_Sie></Pr채sen><Pr채teritum><ich>badete sonnen</ich><du>badetest sonnen</du><er_sie_es>badete sonnen</er_sie_es><wir>badeten sonnen</wir><ihr>badetet sonnen</ihr><sie_Sie>badeten sonnen</sie_Sie></Pr채teritum><Pratizip>hat sonnengebadet </Pratizip></Eintrag>