<?xml version="1.0" encoding="UTF-8"?>
<Eintrag><Stichwort>stillsitzen</Stichwort><Infinitiv>stillsitzen</Infinitiv><Präsen><ich>sitze still</ich><du>sitzt still</du><er_sie_es>sitzt still</er_sie_es><wir>sitzen still</wir><ihr>sitzt still</ihr><sie_Sie>sitzen still</sie_Sie></Präsen><Präteritum><ich>saß still</ich><du>saßest still</du><er_sie_es>saß still</er_sie_es><wir>saßen still</wir><ihr>saßet still</ihr><sie_Sie>saßen still</sie_Sie></Präteritum><Pratizip>hat stillgesessen </Pratizip></Eintrag>