<?xml version="1.0" encoding="UTF-8"?>
<Eintrag><Stichwort>umherschlendern</Stichwort><Infinitiv>umherschlendern</Infinitiv><Pr채sen><ich>schlendere umher</ich><du>schlendre umher</du><er_sie_es>schlenderst umher</er_sie_es><wir>schlendert umher</wir><ihr>schlendern umher</ihr><sie_Sie>schlendert umher</sie_Sie></Pr채sen><Pr채teritum><ich>Sie</ich><du>schlenderte umher</du><er_sie_es>schlendertest umher</er_sie_es><wir>schlenderte umher</wir><ihr>schlenderten umher</ihr><sie_Sie>schlendertet umher</sie_Sie></Pr채teritum><Pratizip>hast umhergeschlendert </Pratizip></Eintrag>