<?xml version="1.0" encoding="UTF-8"?>
<Eintrag><Stichwort>umstrukturieren</Stichwort><Infinitiv>umstrukturieren</Infinitiv><Pr채sen><ich>strukturiere um</ich><du>strukturierst um</du><er_sie_es>strukturiert um</er_sie_es><wir>strukturieren um</wir><ihr>strukturiert um</ihr><sie_Sie>strukturieren um</sie_Sie></Pr채sen><Pr채teritum><ich>strukturierte um</ich><du>strukturiertest um</du><er_sie_es>strukturierte um</er_sie_es><wir>strukturierten um</wir><ihr>strukturiertet um</ihr><sie_Sie>strukturierten um</sie_Sie></Pr채teritum><Pratizip>hat umstrukturiert </Pratizip></Eintrag>