<?xml version="1.0" encoding="UTF-8"?>
<Eintrag><Stichwort>verstümmeln</Stichwort><Infinitiv>verstümmeln</Infinitiv><Präsen><ich>verstümmle</ich><du>verstümmelst</du><er_sie_es>verstümmelt</er_sie_es><wir>verstümmeln</wir><ihr>verstümmelt</ihr><sie_Sie>verstümmeln</sie_Sie></Präsen><Präteritum><ich>verstümmelte</ich><du>verstümmeltest</du><er_sie_es>verstümmelte</er_sie_es><wir>verstümmelten</wir><ihr>verstümmeltet</ihr><sie_Sie>verstümmelten</sie_Sie></Präteritum><Pratizip>hat verstümmelt </Pratizip></Eintrag>