<?xml version="1.0" encoding="UTF-8"?>
<Eintrag><Stichwort>vorbeirennen</Stichwort><Infinitiv>vorbeirennen</Infinitiv><Pr채sen><ich>renne vorbei</ich><du>rennst vorbei</du><er_sie_es>rennt vorbei</er_sie_es><wir>rennen vorbei</wir><ihr>rennt vorbei</ihr><sie_Sie>rennen vorbei</sie_Sie></Pr채sen><Pr채teritum><ich>rannte vorbei</ich><du>ranntest vorbei</du><er_sie_es>rannte vorbei</er_sie_es><wir>rannten vorbei</wir><ihr>ranntet vorbei</ihr><sie_Sie>rannten vorbei</sie_Sie></Pr채teritum><Pratizip>ist vorbeigerannt </Pratizip></Eintrag>