<?xml version="1.0" encoding="UTF-8"?>
<Eintrag><Stichwort>vorkämpfen</Stichwort><Infinitiv>vorkämpfen</Infinitiv><Präsen><ich>kämpfe vor</ich><du>kämpfst vor</du><er_sie_es>kämpft vor</er_sie_es><wir>kämpfen vor</wir><ihr>kämpft vor</ihr><sie_Sie>kämpfen vor</sie_Sie></Präsen><Präteritum><ich>kämpfte vor</ich><du>kämpftest vor</du><er_sie_es>kämpfte vor</er_sie_es><wir>kämpften vor</wir><ihr>kämpftet vor</ihr><sie_Sie>kämpften vor</sie_Sie></Präteritum><Pratizip>hat vorgekämpft </Pratizip></Eintrag>