<?xml version="1.0" encoding="UTF-8"?>
<Eintrag><Stichwort>wegrutschen</Stichwort><Infinitiv>wegrutschen</Infinitiv><Pr채sen><ich>rutsche weg</ich><du>rutscht weg</du><er_sie_es>rutscht weg</er_sie_es><wir>rutschen weg</wir><ihr>rutscht weg</ihr><sie_Sie>rutschen weg</sie_Sie></Pr채sen><Pr채teritum><ich>rutschte weg</ich><du>rutschtest weg</du><er_sie_es>rutschte weg</er_sie_es><wir>rutschten weg</wir><ihr>rutschtet weg</ihr><sie_Sie>rutschten weg</sie_Sie></Pr채teritum><Pratizip>ist weggerutscht </Pratizip></Eintrag>