<?xml version="1.0" encoding="UTF-8"?>
<Eintrag><Stichwort>wegscheuchen</Stichwort><Infinitiv>wegscheuchen</Infinitiv><Pr채sen><ich>scheuche weg</ich><du>scheuchst weg</du><er_sie_es>scheucht weg</er_sie_es><wir>scheuchen weg</wir><ihr>scheucht weg</ihr><sie_Sie>scheuchen weg</sie_Sie></Pr채sen><Pr채teritum><ich>scheuchte weg</ich><du>scheuchtest weg</du><er_sie_es>scheuchte weg</er_sie_es><wir>scheuchten weg</wir><ihr>scheuchtet weg</ihr><sie_Sie>scheuchten weg</sie_Sie></Pr채teritum><Pratizip>hat weggescheucht </Pratizip></Eintrag>