<?xml version="1.0" encoding="UTF-8"?>
<Eintrag><Stichwort>zurückgießen</Stichwort><Infinitiv>zurückgießen</Infinitiv><Präsen><ich>gieße zurück</ich><du>gießt zurück</du><er_sie_es>gießt zurück</er_sie_es><wir>gießen zurück</wir><ihr>gießt zurück</ihr><sie_Sie>gießen zurück</sie_Sie></Präsen><Präteritum><ich>goß zurück</ich><du>gossest zurück</du><er_sie_es>goß zurück</er_sie_es><wir>gossen zurück</wir><ihr>goßt zurück</ihr><sie_Sie>gossen zurück</sie_Sie></Präteritum><Pratizip>hat zurückgegossen </Pratizip></Eintrag>