<?xml version="1.0" encoding="UTF-8"?>
<Eintrag><Stichwort>zusammenstecken</Stichwort><Infinitiv>zusammenstecken</Infinitiv><Pr채sen><ich>stecke zusammen</ich><du>steckst zusammen</du><er_sie_es>steckt zusammen</er_sie_es><wir>stecken zusammen</wir><ihr>steckt zusammen</ihr><sie_Sie>stecken zusammen</sie_Sie></Pr채sen><Pr채teritum><ich>steckte zusammen</ich><du>stecktest zusammen</du><er_sie_es>steckte zusammen</er_sie_es><wir>steckten zusammen</wir><ihr>stecktet zusammen</ihr><sie_Sie>steckten zusammen</sie_Sie></Pr채teritum><Pratizip>hat zusammengesteckt </Pratizip></Eintrag>