<?xml version="1.0" encoding="utf-8" standalone="yes"?><!DOCTYPE Entry SYSTEM "NounModel.dtd"><?xml-stylesheet type="text/xsl" href="NounRenderTemplate2.xslt"?><Entry category="Substantiv">
  <Stichwort>Enkelkind</Stichwort>
  <Einheit>4</Einheit>
  <Anteil>Einführung</Anteil>
  <Genus>das</Genus>
  <Pluralform>Enkelkinder</Pluralform>
  <GenitivSingular/>
  <zusammengesetzteWörter>
    <KompositaCollection/>
    <abgeleiteteWörter/>
  </zusammengesetzteWörter>
  <Synonymegruppe/>
  <Antonymegruppe/>
  <Kollokationen/>
  <AllgemeineErläuterungen>
    <Eintrag>
      <Chinesisch>孙子</Chinesisch>
      <BeispielSammlung>
        <Beispiel>
          <Satz>Alex ist Marias Enkelkind.</Satz>
          <Übersetzung>Alex 是 Maria 的孙子。</Übersetzung>
        </Beispiel>
      </BeispielSammlung>
    </Eintrag>
  </AllgemeineErläuterungen>
</Entry>
