<?xml version="1.0" encoding="UTF-8"?><!DOCTYPE Entry SYSTEM "VerbenModel.dtd"><?xml-stylesheet type="text/xsl" href="VerbRenderTemplate.xslt"?><Entry category="Verben">
	<Stichwort>schließen</Stichwort>
	<Einheit>2</Einheit>
	<Anteil>Text</Anteil>
	<Konjugation>
				<Präsen>
					<ich>schließe</ich>
					<du>schließt</du>
					<er_sie_es>schließt</er_sie_es>
					<wir>schließen</wir>
					<ihr>schließt</ihr>
					<sie_Sie>schließen</sie_Sie>
				</Präsen>
				<Präteritum>
					<ich>schloß</ich>
					<du>schlossest</du>
					<er_sie_es>schloß</er_sie_es>
					<wir>schlossen</wir>
					<ihr>schloßt</ihr>
					<sie_Sie>schlossen</sie_Sie>
				</Präteritum>
				<Perfekt hilfsverb="haben">	
					<ich>habe geschlossen</ich>
					<du>hast geschlossen</du>
					<er_sie_es>hat geschlossen</er_sie_es>
					<wir>haben geschlossen</wir>
					<ihr>habt geschlossen</ihr>
					<sie_Sie>haben geschlossen</sie_Sie>
				</Perfekt>
	</Konjugation>
			
			
	<zusammengesetzteWörter>
			<KompositaCollection>
			</KompositaCollection>
			<abgeleiteteWörter>
			</abgeleiteteWörter>
	</zusammengesetzteWörter>
		<Synonymegruppe>
      <Sym>zumachen</Sym>
      <Sym>abschließen</Sym>
		</Synonymegruppe>
		<Antonymegruppe>
      <Anm>aufmachen</Anm>
      <Anm>aufschließen</Anm>
      <Anm>öffnen</Anm>
		</Antonymegruppe>

		<Kollokationen>
      <K>das Fenster schließen</K>
      <K>die Tür schließen</K>

    </Kollokationen>
		<AllgemeineErläuterungen>
				<Eintrag transitiv="">
					
					<Chinesisch>合，关，闭，锁</Chinesisch>
					<BeispielSammlung>
					<Beispiel>
					<Satz>Die Studenten schließen die Bücher.</Satz>
            <Übersetzung>同学们合上了书。</Übersetzung>
					</Beispiel>
					</BeispielSammlung>
					
   				</Eintrag>
			</AllgemeineErläuterungen>
	
	
</Entry>
